libra_ai/__init__.py
libra_ai/client.py
libra_ai_sdk-1.0.2.dist-info/METADATA
libra_ai_sdk-1.0.2.dist-info/WHEEL
libra_ai_sdk-1.0.2.dist-info/top_level.txt
libra_ai_sdk-1.0.2.dist-info/RECORD
