Metadata-Version: 2.4
Name: libra-ai-sdk
Version: 1.0.2
Summary: Official Libra AI SDK for Python
Author-email: IndoNusaCorp <dev@libra-ai.com>
License: MIT
Project-URL: Homepage, https://libra-ai.com
Project-URL: Documentation, https://libra-ai.com/docs
Project-URL: Repository, https://github.com/indonusacorp/libra-ai-sdk-python
Project-URL: Issues, https://github.com/indonusacorp/libra-ai-sdk-python/issues
Keywords: libra,libra-ai,ai,chatbot,sdk,api,gemini
Classifier: Development Status :: 4 - Beta
Classifier: Intended Audience :: Developers
Classifier: License :: OSI Approved :: MIT License
Classifier: Operating System :: OS Independent
Classifier: Programming Language :: Python :: 3
Classifier: Programming Language :: Python :: 3.8
Classifier: Programming Language :: Python :: 3.9
Classifier: Programming Language :: Python :: 3.10
Classifier: Programming Language :: Python :: 3.11
Classifier: Programming Language :: Python :: 3.12
Classifier: Topic :: Software Development :: Libraries :: Python Modules
Classifier: Topic :: Scientific/Engineering :: Artificial Intelligence
Requires-Python: >=3.8
Requires-Dist: requests>=2.25.0
Provides-Extra: dev
Requires-Dist: pytest>=7.0; extra == "dev"
Requires-Dist: pytest-asyncio>=0.20; extra == "dev"
Requires-Dist: black>=23.0; extra == "dev"
Requires-Dist: mypy>=1.0; extra == "dev"
